{"cameraMode":{"drawMode":0,"name":"Shaded","section":"Shading Mode"},"sceneLighting":false,"audioPlay":false,"sceneViewState":{"m_AlwaysRefresh":false,"showFog":true,"showSkybox":false,"showFlares":true,"showImageEffects":true,"showParticleSystems":true,"showVisualEffectGraphs":true,"m_FxEnabled":false},"in2DMode":false,"pivot":{"x":0.0,"y":0.5752319693565369,"z":0.013246387243270874},"rotation":{"x":0.01807837001979351,"y":-0.9809756278991699,"z":0.11321355402469635,"w":0.1566818654537201},"size":0.7723356485366821,"orthographic":false}